dunderdecorators/__init__.py
dunderdecorators/dunder_decorators.py
dunderdecorators/exceptions.py
dunderdecorators-1.0.0.dist-info/METADATA
dunderdecorators-1.0.0.dist-info/WHEEL
dunderdecorators-1.0.0.dist-info/top_level.txt
dunderdecorators-1.0.0.dist-info/RECORD
