Metadata-Version: 2.1
Name: dunderdecorators
Version: 1.0.0
Summary: Python decorator library that adds customizeable dunder methods to decorated classes.
Home-page: https://github.com/astokely/dunderdecorators
Author: Andy Stokely
Author-email: amstokely@ucsd.edu
License: MIT
Platform: Linux
Platform: Unix
Requires-Python: >=3.6
Requires-Dist: typing
Requires-Dist: pytest
Requires-Dist: cython
